EasyDonateClient
