Metadata-Version: 2.1
Name: EasyDonateClient
Version: 0.0.2
Summary: Неофициальный модуль для EasyDonateApi.
Author: TheFilik
Author-email: filikt415@gmail.com
